model_parameter_upload/__init__.py
model_parameter_upload/upload_params.py
model_parameter_upload-0.1.2.dist-info/LICENSE
model_parameter_upload-0.1.2.dist-info/METADATA
model_parameter_upload-0.1.2.dist-info/WHEEL
model_parameter_upload-0.1.2.dist-info/top_level.txt
model_parameter_upload-0.1.2.dist-info/RECORD
