Metadata-Version: 2.1
Name: model-parameter-upload
Version: 0.1.2
Summary: upload model params to target address
Home-page: https://github.com/wdxdxdd/model_parameter_upload
Author: Dash
Author-email: Dash@google.com
License: UNKNOWN
Platform: UNKNOWN
Classifier: Programming Language :: Python :: 3.9
Classifier: License :: OSI Approved :: MIT License
Classifier: Operating System :: OS Independent
Requires-Python: >=3.6
License-File: LICENSE
Requires-Dist: requests
